{
  "generator-jhipster": {
    "applicationType": "microservice",
    "gitHubOrganization": "msenthilkumarsam",
    "baseName": "SampleMicroservice",
    "packageName": "com.web.infinite",
    "serverPort": 8081,
    "serviceDiscoveryType": "eureka",
    "authenticationType": "jwt",
    "uaaBaseName": "../uaa",
    "cacheProvider": "no",
    "enableHibernateCache": false,
    "websocket": false,
    "databaseType": "sql",
    "devDatabaseType": "mysql",
    "prodDatabaseType": "mysql",
    "searchEngine": false,
    "enableSwaggerCodegen": false,
    "messageBroker": false,
    "buildTool": "maven",
    "enableSocialSignIn": false,
    "useSass": false,
    "clientPackageManager": "yarn",
    "testFrameworks": [],
    "enableTranslation": false,
    "nativeLanguage": "en",
    "languages": [
      "en"
    ],
    "clientFramework": "angularX",
    "jhipsterVersion": "4.14.0",
    "packageFolder": "com/web/infinite",
    "jwtSecretKey": "6ee2d177f6c9231aba86cc298518ecfa152d1d45",
    "jhiPrefix": "jhi",
    "skipClient": true,
    "skipUserManagement": true
  }
}